{
  "Number": 8303,
  "Name": "Aman Jungle3",
  "WalkSpot": "0, 0",
  "Description": null,
  "DisplayName": "Aman Jungle",
  "Size": {
    "Width": 100,
    "Height": 100
  },
  "Flags": 0,
  "Portals": {
    "99, 68": {
      "MapId": 8304,
      "X": 1,
      "Y": 68,
      "Point": "1, 68"
    },
    "99, 67": {
      "MapId": 8304,
      "X": 1,
      "Y": 67,
      "Point": "1, 67"
    },
    "99, 66": {
      "MapId": 8304,
      "X": 1,
      "Y": 66,
      "Point": "1, 66"
    },
    "99, 65": {
      "MapId": 8304,
      "X": 1,
      "Y": 65,
      "Point": "1, 65"
    },
    "99, 64": {
      "MapId": 8304,
      "X": 1,
      "Y": 64,
      "Point": "1, 64"
    },
    "99, 63": {
      "MapId": 8304,
      "X": 1,
      "Y": 63,
      "Point": "1, 63"
    },
    "99, 62": {
      "MapId": 8304,
      "X": 1,
      "Y": 62,
      "Point": "1, 62"
    },
    "99, 61": {
      "MapId": 8304,
      "X": 1,
      "Y": 61,
      "Point": "1, 61"
    },
    "99, 60": {
      "MapId": 8304,
      "X": 1,
      "Y": 60,
      "Point": "1, 60"
    },
    "99, 59": {
      "MapId": 8304,
      "X": 1,
      "Y": 59,
      "Point": "1, 59"
    },
    "99, 58": {
      "MapId": 8304,
      "X": 1,
      "Y": 58,
      "Point": "1, 58"
    },
    "99, 57": {
      "MapId": 8304,
      "X": 1,
      "Y": 57,
      "Point": "1, 57"
    },
    "0, 39": {
      "MapId": 8318,
      "X": 97,
      "Y": 39,
      "Point": "97, 39"
    },
    "0, 38": {
      "MapId": 8318,
      "X": 98,
      "Y": 38,
      "Point": "98, 38"
    },
    "0, 37": {
      "MapId": 8318,
      "X": 98,
      "Y": 37,
      "Point": "98, 37"
    },
    "0, 36": {
      "MapId": 8318,
      "X": 98,
      "Y": 36,
      "Point": "98, 36"
    },
    "0, 34": {
      "MapId": 8318,
      "X": 98,
      "Y": 34,
      "Point": "98, 34"
    },
    "0, 33": {
      "MapId": 8318,
      "X": 98,
      "Y": 33,
      "Point": "98, 33"
    },
    "0, 35": {
      "MapId": 8318,
      "X": 98,
      "Y": 35,
      "Point": "98, 35"
    },
    "0, 32": {
      "MapId": 8318,
      "X": 98,
      "Y": 32,
      "Point": "98, 32"
    },
    "0, 31": {
      "MapId": 8318,
      "X": 98,
      "Y": 31,
      "Point": "98, 31"
    },
    "0, 30": {
      "MapId": 8318,
      "X": 98,
      "Y": 30,
      "Point": "98, 30"
    },
    "0, 29": {
      "MapId": 8318,
      "X": 98,
      "Y": 29,
      "Point": "98, 29"
    },
    "0, 28": {
      "MapId": 8318,
      "X": 98,
      "Y": 28,
      "Point": "98, 28"
    }
  },
  "WorldMaps": {}
}